katka/__init__.py
katka/admin.py
katka/apps.py
katka/auditedmodel.py
katka/auth.py
katka/constants.py
katka/exceptions.py
katka/fields.py
katka/models.py
katka/permissions.py
katka/releases.py
katka/serializer_fields.py
katka/serializers.py
katka/signals.py
katka/urls.py
katka/utils.py
katka/views.py
katka/viewsets.py
katka/migrations/0001_initial.py
katka/migrations/0002_add_project_and_slug.py
katka/migrations/0003_credential_and_unique_slugs.py
katka/migrations/0004_credential_secret.py
katka/migrations/0005_scmservice.py
katka/migrations/0006_application_and_scm_repository.py
katka/migrations/0007_remove_status_add_deleted.py
katka/migrations/0008_scmpipelinerun.py
katka/migrations/0009_scmsteprun.py
katka/migrations/0010_rename_scmtype.py
katka/migrations/0011_auto_20190318_0806.py
katka/migrations/0012_scmrelease.py
katka/migrations/0013_update_step_statuses.py
katka/migrations/0014_update_pipeline_statuses.py
katka/migrations/0015_update_pipeline_statuses_fix.py
katka/migrations/0016_auto_20190425_0922.py
katka/migrations/0017_auto_20190501_0917.py
katka/migrations/0018_auto_20190506_0425.py
katka/migrations/0019_scmsteprun_sequence_id.py
katka/migrations/0020_multiple_pipeline_runs_per_release.py
katka/migrations/0021_added_step_tags.py
katka/migrations/0022_change_release_status_fields.py
katka/migrations/0023_auto_20191024_0825.py
katka/migrations/0024_scmsteprun_started_ended.py
katka/migrations/0025_datetime_field_names.py
katka/migrations/0026_scmsteprun_step_type.py
katka/migrations/0027_commit_ordering.py
katka/migrations/0028_unique_commits.py
katka/migrations/0029_release_pipeline_run_created_at_ordering.py
katka/migrations/0030_unique_team_credentialname.py
katka/migrations/0031_application_active.py
katka/migrations/0032_added_step_aborted.py
katka/migrations/0033_scmpipelinerun_output.py
katka/migrations/0034_team_sys_users.py
katka/migrations/__init__.py
tests/__init__.py
tests/settings.py
tests/unit/__init__.py
tests/unit/conftest.py
katka_core-0.51.0.dist-info/LICENSE
katka_core-0.51.0.dist-info/METADATA
katka_core-0.51.0.dist-info/WHEEL
katka_core-0.51.0.dist-info/top_level.txt
katka_core-0.51.0.dist-info/RECORD
