Metadata-Version: 2.1
Name: katka-core
Version: 0.51.0
Summary: Katka Django core application
Home-page: https://github.com/kpn/katka-core
Author: D-Nitro
Author-email: d-nitro@kpn.com
License: UNKNOWN
Platform: UNKNOWN
Classifier: Development Status :: 3 - Alpha
Classifier: Framework :: Django :: 2.1
Classifier: Intended Audience :: Developers
Classifier: Natural Language :: English
Classifier: Operating System :: OS Independent
Classifier: Programming Language :: Python :: 3.7
Classifier: Programming Language :: Python :: 3.8
Classifier: Topic :: Internet :: WWW/HTTP
Requires-Dist: Django (<3.0,>=2.2.9)
Requires-Dist: djangorestframework (<4.0.0,>=3.9.0)
Requires-Dist: django-encrypted-model-fields (<1.0.0,>=0.5.8)
Requires-Dist: drf-nested-routers
